pygeoguz/__init__.py
pygeoguz/adjustment.py
pygeoguz/objects.py
pygeoguz/simplegeo.py
pygeoguz/transform.py
pygeoguz-0.0.4.dist-info/METADATA
pygeoguz-0.0.4.dist-info/WHEEL
pygeoguz-0.0.4.dist-info/top_level.txt
pygeoguz-0.0.4.dist-info/RECORD
