Metadata-Version: 2.1
Name: pygeoguz
Version: 0.0.4
Summary: Solution of the geodesy tasks in Python
Home-page: https://github.com/Andrpocc/pygeoguz
Author: Andrey Pochatkov
Author-email: andrey.pochatkov@mail.ru
License: UNKNOWN
Keywords: geodesy
Platform: UNKNOWN
Classifier: Programming Language :: Python :: 3
Classifier: Operating System :: OS Independent
Requires-Python: >=3.7
